{
  "variants": {
    "variant=asurine": {
      "model": "create:orestone/pillar_z/asurine"
    },
    "variant=crimsite": {
      "model": "create:orestone/pillar_z/crimsite"
    },
    "variant=limestone": {
      "model": "create:orestone/pillar_z/limestone"
    },
    "variant=ochrum": {
      "model": "create:orestone/pillar_z/ochrum"
    },
    "variant=scorchia": {
      "model": "create:orestone/pillar_z/scorchia"
    },
    "variant=scoria": {
      "model": "create:orestone/pillar_z/scoria"
    },
    "variant=veridium": {
      "model": "create:orestone/pillar_z/veridium"
    }
  }
}